<?xml version="1.0" encoding="utf-8"?>
<odoo>
    <record id="view_hr_payslip_form_work_days" model="ir.ui.view">
        <field name="name">view.hr.payslip.form.work.days</field>
        <field name="model">hr.payslip</field>
        <field name="inherit_id" ref="hr_payroll.view_hr_payslip_form"/>
        <field name="arch" type="xml">
            <xpath expr="//field[@name='number_of_hours']" position="attributes">
                <attribute name="invisible">1</attribute>
            </xpath>
            <xpath expr="//field[@name='amount']" position="attributes">
                <attribute name="readonly">1</attribute>
            </xpath>
        </field>
    </record>
</odoo>